{
"meta":{"test_sets":[],"test_metrics":[],"learn_metrics":[{"best_value":"Min","name":"RMSE"}],"launch_mode":"Train","parameters":"","iteration_count":256,"learn_sets":["learn"],"name":"experiment"},
"iterations":[
{"learn":[14.48906053],"iteration":0,"passed_time":0.001026984535,"remaining_time":0.2618810564},
{"learn":[14.02225494],"iteration":1,"passed_time":0.00181781033,"remaining_time":0.230861912},
{"learn":[13.60354732],"iteration":2,"passed_time":0.002572499998,"remaining_time":0.2169474998},
{"learn":[13.15919147],"iteration":3,"passed_time":0.003188262465,"remaining_time":0.2008605353},
{"learn":[12.75735],"iteration":4,"passed_time":0.004019978676,"remaining_time":0.2018029295},
{"learn":[12.41433471],"iteration":5,"passed_time":0.005324514663,"remaining_time":0.2218547776},
{"learn":[12.04332751],"iteration":6,"passed_time":0.006187103401,"remaining_time":0.2200841067},
{"learn":[11.7159182],"iteration":7,"passed_time":0.007093415563,"remaining_time":0.2198958825},
{"learn":[11.40918526],"iteration":8,"passed_time":0.007889190043,"remaining_time":0.2165144379},
{"learn":[11.06317149],"iteration":9,"passed_time":0.008638461747,"remaining_time":0.212506159},
{"learn":[10.74512018],"iteration":10,"passed_time":0.009405370414,"remaining_time":0.2094832501},
{"learn":[10.47284173],"iteration":11,"passed_time":0.0103121597,"remaining_time":0.2096805805},
{"learn":[10.22645161],"iteration":12,"passed_time":0.01109654808,"remaining_time":0.2074200909},
{"learn":[9.996941914],"iteration":13,"passed_time":0.01187244568,"remaining_time":0.2052237039},
{"learn":[9.738907396],"iteration":14,"passed_time":0.01262950733,"remaining_time":0.2029140845},
{"learn":[9.483581501],"iteration":15,"passed_time":0.0132822607,"remaining_time":0.1992339106},
{"learn":[9.248762967],"iteration":16,"passed_time":0.01407984833,"remaining_time":0.1979461029},
{"learn":[9.044423454],"iteration":17,"passed_time":0.01483796575,"remaining_time":0.1961908805},
{"learn":[8.830480782],"iteration":18,"passed_time":0.01549988017,"remaining_time":0.1933406106},
{"learn":[8.640430273],"iteration":19,"passed_time":0.01617103117,"remaining_time":0.1908181678},
{"learn":[8.469232316],"iteration":20,"passed_time":0.01684452857,"remaining_time":0.1884982959},
{"learn":[8.293038317],"iteration":21,"passed_time":0.01761405026,"remaining_time":0.1873494436},
{"learn":[8.134457778],"iteration":22,"passed_time":0.0183500542,"remaining_time":0.1858940274},
{"learn":[7.971516779],"iteration":23,"passed_time":0.0190825074,"remaining_time":0.1844642382},
{"learn":[7.817057171],"iteration":24,"passed_time":0.01974524192,"remaining_time":0.1824460353},
{"learn":[7.687055177],"iteration":25,"passed_time":0.02039678969,"remaining_time":0.1804331396},
{"learn":[7.568147707],"iteration":26,"passed_time":0.02114471423,"remaining_time":0.1793385022},
{"learn":[7.468289508],"iteration":27,"passed_time":0.02175609057,"remaining_time":0.1771567375},
{"learn":[7.347085123],"iteration":28,"passed_time":0.0223560742,"remaining_time":0.1749940981},
{"learn":[7.238066519],"iteration":29,"passed_time":0.02302152865,"remaining_time":0.1734288491},
{"learn":[7.129730794],"iteration":30,"passed_time":0.02364531467,"remaining_time":0.1716192194},
{"learn":[7.024393974],"iteration":31,"passed_time":0.02427968072,"remaining_time":0.1699577651},
{"learn":[6.925199123],"iteration":32,"passed_time":0.02491607248,"remaining_time":0.1683722474},
{"learn":[6.847811332],"iteration":33,"passed_time":0.02553101361,"remaining_time":0.1667025006},
{"learn":[6.755863872],"iteration":34,"passed_time":0.02622405191,"remaining_time":0.1655861563},
{"learn":[6.668564977],"iteration":35,"passed_time":0.02681462066,"remaining_time":0.1638671263},
{"learn":[6.593058094],"iteration":36,"passed_time":0.02741953358,"remaining_time":0.1622939961},
{"learn":[6.524365189],"iteration":37,"passed_time":0.02801697436,"remaining_time":0.1607289582},
{"learn":[6.462115348],"iteration":38,"passed_time":0.02869910409,"remaining_time":0.1596847587},
{"learn":[6.400842955],"iteration":39,"passed_time":0.02929738272,"remaining_time":0.1582058667},
{"learn":[6.344499875],"iteration":40,"passed_time":0.02997279149,"remaining_time":0.1571743944},
{"learn":[6.293484608],"iteration":41,"passed_time":0.03074741581,"remaining_time":0.1566654044},
{"learn":[6.24087202],"iteration":42,"passed_time":0.03167706893,"remaining_time":0.1569119926},
{"learn":[6.198546265],"iteration":43,"passed_time":0.03228626809,"remaining_time":0.1555611099},
{"learn":[6.147335606],"iteration":44,"passed_time":0.03288804176,"remaining_time":0.1542083736},
{"learn":[6.093775884],"iteration":45,"passed_time":0.03352029503,"remaining_time":0.1530274338},
{"learn":[6.050513246],"iteration":46,"passed_time":0.03423397541,"remaining_time":0.1522319332},
{"learn":[6.006693727],"iteration":47,"passed_time":0.0348089296,"remaining_time":0.1508386949},
{"learn":[5.96089276],"iteration":48,"passed_time":0.03532516985,"remaining_time":0.1492308196},
{"learn":[5.918196519],"iteration":49,"passed_time":0.03607387322,"remaining_time":0.1486243577},
{"learn":[5.88272917],"iteration":50,"passed_time":0.03676018767,"remaining_time":0.1477615387},
{"learn":[5.8511336],"iteration":51,"passed_time":0.03738092234,"remaining_time":0.1466482338},
{"learn":[5.81584368],"iteration":52,"passed_time":0.03798337661,"remaining_time":0.1454834991},
{"learn":[5.782817455],"iteration":53,"passed_time":0.03859418791,"remaining_time":0.1443708511},
{"learn":[5.752000872],"iteration":54,"passed_time":0.03920028125,"remaining_time":0.1432592097},
{"learn":[5.726572835],"iteration":55,"passed_time":0.03973657379,"remaining_time":0.141916335},
{"learn":[5.698917139],"iteration":56,"passed_time":0.04026485887,"remaining_time":0.1405738055},
{"learn":[5.676518895],"iteration":57,"passed_time":0.04082605291,"remaining_time":0.1393716979},
{"learn":[5.655940507],"iteration":58,"passed_time":0.0413795024,"remaining_time":0.1381654572},
{"learn":[5.636103831],"iteration":59,"passed_time":0.04197161271,"remaining_time":0.1371072682},
{"learn":[5.611404849],"iteration":60,"passed_time":0.04265966683,"remaining_time":0.1363710661},
{"learn":[5.588301345],"iteration":61,"passed_time":0.04330514741,"remaining_time":0.1355032032},
{"learn":[5.565889892],"iteration":62,"passed_time":0.04382570652,"remaining_time":0.1342597041},
{"learn":[5.539865651],"iteration":63,"passed_time":0.04450678708,"remaining_time":0.1335203612},
{"learn":[5.520455813],"iteration":64,"passed_time":0.04507309902,"remaining_time":0.1324455679},
{"learn":[5.499997499],"iteration":65,"passed_time":0.04579598916,"remaining_time":0.1318369385},
{"learn":[5.48268047],"iteration":66,"passed_time":0.04655703948,"remaining_time":0.1313325442},
{"learn":[5.461563181],"iteration":67,"passed_time":0.04727952844,"remaining_time":0.1307139904},
{"learn":[5.449566952],"iteration":68,"passed_time":0.04787180054,"remaining_time":0.1297395174},
{"learn":[5.431414573],"iteration":69,"passed_time":0.04863011938,"remaining_time":0.1292171744},
{"learn":[5.411391195],"iteration":70,"passed_time":0.04932558539,"remaining_time":0.1285244126},
{"learn":[5.401950923],"iteration":71,"passed_time":0.04991298929,"remaining_time":0.1275554171},
{"learn":[5.389055706],"iteration":72,"passed_time":0.05062771142,"remaining_time":0.1269160437},
{"learn":[5.376409829],"iteration":73,"passed_time":0.05126861849,"remaining_time":0.1260930887},
{"learn":[5.362883706],"iteration":74,"passed_time":0.05186693509,"remaining_time":0.1251722034},
{"learn":[5.351001093],"iteration":75,"passed_time":0.05244476892,"remaining_time":0.1242112948},
{"learn":[5.342058679],"iteration":76,"passed_time":0.0529523141,"remaining_time":0.123096938},
{"learn":[5.333472939],"iteration":77,"passed_time":0.05349716964,"remaining_time":0.1220832846},
{"learn":[5.323751558],"iteration":78,"passed_time":0.05410011588,"remaining_time":0.121211652},
{"learn":[5.308601135],"iteration":79,"passed_time":0.05463975528,"remaining_time":0.1202074616},
{"learn":[5.304390939],"iteration":80,"passed_time":0.05501084678,"remaining_time":0.1188505949},
{"learn":[5.292213733],"iteration":81,"passed_time":0.05558585214,"remaining_time":0.1179504667},
{"learn":[5.28120348],"iteration":82,"passed_time":0.05625743239,"remaining_time":0.1172594675},
{"learn":[5.270115932],"iteration":83,"passed_time":0.0568287314,"remaining_time":0.1163635929},
{"learn":[5.264979551],"iteration":84,"passed_time":0.0571625761,"remaining_time":0.1149976531},
{"learn":[5.255314542],"iteration":85,"passed_time":0.05774491947,"remaining_time":0.1141469338},
{"learn":[5.250781355],"iteration":86,"passed_time":0.05815529749,"remaining_time":0.1129683365},
{"learn":[5.236993842],"iteration":87,"passed_time":0.05881486469,"remaining_time":0.1122829235},
{"learn":[5.223666913],"iteration":88,"passed_time":0.05940979357,"remaining_time":0.1114768037},
{"learn":[5.212780596],"iteration":89,"passed_time":0.05997644808,"remaining_time":0.1106232265},
{"learn":[5.206345172],"iteration":90,"passed_time":0.06053074492,"remaining_time":0.1097535485},
{"learn":[5.197603235],"iteration":91,"passed_time":0.0611821569,"remaining_time":0.1090638449},
{"learn":[5.186533071],"iteration":92,"passed_time":0.06186665284,"remaining_time":0.1084329507},
{"learn":[5.182185788],"iteration":93,"passed_time":0.06219674991,"remaining_time":0.1071901435},
{"learn":[5.171870188],"iteration":94,"passed_time":0.06286167605,"remaining_time":0.1065339984},
{"learn":[5.163542452],"iteration":95,"passed_time":0.06346487035,"remaining_time":0.1057747839},
{"learn":[5.163119374],"iteration":96,"passed_time":0.06374305782,"remaining_time":0.1044860432},
{"learn":[5.15256374],"iteration":97,"passed_time":0.06432823296,"remaining_time":0.1037128654},
{"learn":[5.144877981],"iteration":98,"passed_time":0.06490538661,"remaining_time":0.1029307646},
{"learn":[5.140240422],"iteration":99,"passed_time":0.06542888315,"remaining_time":0.1020690577},
{"learn":[5.129971962],"iteration":100,"passed_time":0.06592898218,"remaining_time":0.101178141},
{"learn":[5.121855004],"iteration":101,"passed_time":0.0664886037,"remaining_time":0.1003847546},
{"learn":[5.11334142],"iteration":102,"passed_time":0.06706340848,"remaining_time":0.09961846114},
{"learn":[5.104138464],"iteration":103,"passed_time":0.06770175701,"remaining_time":0.09894872178},
{"learn":[5.09976708],"iteration":104,"passed_time":0.06827723496,"remaining_time":0.09818916646},
{"learn":[5.094168591],"iteration":105,"passed_time":0.06888514556,"remaining_time":0.09747897957},
{"learn":[5.089045125],"iteration":106,"passed_time":0.06952935492,"remaining_time":0.09682125124},
{"learn":[5.079200796],"iteration":107,"passed_time":0.07004800472,"remaining_time":0.09599171017},
{"learn":[5.072248379],"iteration":108,"passed_time":0.07056159645,"remaining_time":0.0951610521},
{"learn":[5.0652743],"iteration":109,"passed_time":0.07110600582,"remaining_time":0.09437706227},
{"learn":[5.061189088],"iteration":110,"passed_time":0.07161362158,"remaining_time":0.09354932549},
{"learn":[5.051910168],"iteration":111,"passed_time":0.07213156519,"remaining_time":0.09274058381},
{"learn":[5.044075152],"iteration":112,"passed_time":0.07270334421,"remaining_time":0.09200511701},
{"learn":[5.039775108],"iteration":113,"passed_time":0.07340330076,"remaining_time":0.09143218165},
{"learn":[5.031587627],"iteration":114,"passed_time":0.07400151335,"remaining_time":0.09073229029},
{"learn":[5.026941043],"iteration":115,"passed_time":0.07454348264,"remaining_time":0.08996627215},
{"learn":[5.022746],"iteration":116,"passed_time":0.07527185595,"remaining_time":0.08942553827},
{"learn":[5.016599316],"iteration":117,"passed_time":0.07586488378,"remaining_time":0.08872333865},
{"learn":[5.008152585],"iteration":118,"passed_time":0.07656290543,"remaining_time":0.08814384911},
{"learn":[5.004898074],"iteration":119,"passed_time":0.0771952301,"remaining_time":0.08748792745},
{"learn":[4.998627337],"iteration":120,"passed_time":0.07785980212,"remaining_time":0.08686837427},
{"learn":[4.994807853],"iteration":121,"passed_time":0.07839747649,"remaining_time":0.08610870369},
{"learn":[4.989789709],"iteration":122,"passed_time":0.0789792767,"remaining_time":0.08540035611},
{"learn":[4.983325442],"iteration":123,"passed_time":0.07962218636,"remaining_time":0.08475910161},
{"learn":[4.978309514],"iteration":124,"passed_time":0.08027211085,"remaining_time":0.08412517217},
{"learn":[4.973129018],"iteration":125,"passed_time":0.08102653843,"remaining_time":0.08359880949},
{"learn":[4.971429647],"iteration":126,"passed_time":0.08168144503,"remaining_time":0.082967767},
{"learn":[4.967489337],"iteration":127,"passed_time":0.08225544209,"remaining_time":0.08225544209},
{"learn":[4.965365253],"iteration":128,"passed_time":0.08283861258,"remaining_time":0.081554293},
{"learn":[4.962312215],"iteration":129,"passed_time":0.0834079899,"remaining_time":0.08084159021},
{"learn":[4.956984939],"iteration":130,"passed_time":0.08394917664,"remaining_time":0.08010417618},
{"learn":[4.953429416],"iteration":131,"passed_time":0.08455163915,"remaining_time":0.07942729739},
{"learn":[4.945239304],"iteration":132,"passed_time":0.08502249225,"remaining_time":0.07862982366},
{"learn":[4.938404554],"iteration":133,"passed_time":0.08561892142,"remaining_time":0.07795155532},
{"learn":[4.932089676],"iteration":134,"passed_time":0.0863357943,"remaining_time":0.07738245267},
{"learn":[4.928068645],"iteration":135,"passed_time":0.0869871939,"remaining_time":0.07675340638},
{"learn":[4.922207553],"iteration":136,"passed_time":0.0875311084,"remaining_time":0.0760306708},
{"learn":[4.91737021],"iteration":137,"passed_time":0.08816225843,"remaining_time":0.07538511953},
{"learn":[4.910071973],"iteration":138,"passed_time":0.08869448884,"remaining_time":0.07465651219},
{"learn":[4.900370311],"iteration":139,"passed_time":0.08929219913,"remaining_time":0.073984965},
{"learn":[4.895671161],"iteration":140,"passed_time":0.08989397569,"remaining_time":0.07331778159},
{"learn":[4.890098002],"iteration":141,"passed_time":0.09043241568,"remaining_time":0.07260067174},
{"learn":[4.887352734],"iteration":142,"passed_time":0.09100986897,"remaining_time":0.07191688947},
{"learn":[4.880657277],"iteration":143,"passed_time":0.09149126,"remaining_time":0.07115986889},
{"learn":[4.877795884],"iteration":144,"passed_time":0.09201636166,"remaining_time":0.07044011134},
{"learn":[4.871797273],"iteration":145,"passed_time":0.09260817604,"remaining_time":0.06977328332},
{"learn":[4.867615812],"iteration":146,"passed_time":0.09331902548,"remaining_time":0.06919573999},
{"learn":[4.865186241],"iteration":147,"passed_time":0.09397560696,"remaining_time":0.06857679427},
{"learn":[4.859010581],"iteration":148,"passed_time":0.09459266913,"remaining_time":0.06792896374},
{"learn":[4.854683211],"iteration":149,"passed_time":0.09520178451,"remaining_time":0.06727592772},
{"learn":[4.847837606],"iteration":150,"passed_time":0.09610577505,"remaining_time":0.06682851907},
{"learn":[4.846830944],"iteration":151,"passed_time":0.09648003139,"remaining_time":0.06601265305},
{"learn":[4.843255543],"iteration":152,"passed_time":0.09708218518,"remaining_time":0.06535598087},
{"learn":[4.839750373],"iteration":153,"passed_time":0.09768862934,"remaining_time":0.0647028584},
{"learn":[4.834143945],"iteration":154,"passed_time":0.09830306281,"remaining_time":0.06405554415},
{"learn":[4.825870346],"iteration":155,"passed_time":0.0990046542,"remaining_time":0.06346452193},
{"learn":[4.823744293],"iteration":156,"passed_time":0.09961018788,"remaining_time":0.06281151974},
{"learn":[4.819754416],"iteration":157,"passed_time":0.100184194,"remaining_time":0.06213956338},
{"learn":[4.817027034],"iteration":158,"passed_time":0.1009299352,"remaining_time":0.06157360826},
{"learn":[4.813701569],"iteration":159,"passed_time":0.1015623304,"remaining_time":0.06093739826},
{"learn":[4.811064063],"iteration":160,"passed_time":0.1021944681,"remaining_time":0.06030108368},
{"learn":[4.804551623],"iteration":161,"passed_time":0.1029805504,"remaining_time":0.05975414652},
{"learn":[4.80014012],"iteration":162,"passed_time":0.1035254286,"remaining_time":0.05906665559},
{"learn":[4.795765075],"iteration":163,"passed_time":0.1041328943,"remaining_time":0.05841601387},
{"learn":[4.79025872],"iteration":164,"passed_time":0.1048567969,"remaining_time":0.05783011221},
{"learn":[4.785587743],"iteration":165,"passed_time":0.1054795601,"remaining_time":0.05718771333},
{"learn":[4.778402121],"iteration":166,"passed_time":0.1061442799,"remaining_time":0.05656790966},
{"learn":[4.77396725],"iteration":167,"passed_time":0.1066769891,"remaining_time":0.05587842286},
{"learn":[4.770607643],"iteration":168,"passed_time":0.1073766687,"remaining_time":0.05527674661},
{"learn":[4.766542314],"iteration":169,"passed_time":0.1079322991,"remaining_time":0.05460104542},
{"learn":[4.763720652],"iteration":170,"passed_time":0.1085066272,"remaining_time":0.05393604274},
{"learn":[4.755761465],"iteration":171,"passed_time":0.10902885,"remaining_time":0.05324664767},
{"learn":[4.753174532],"iteration":172,"passed_time":0.1096327117,"remaining_time":0.052598353},
{"learn":[4.749824782],"iteration":173,"passed_time":0.1101264422,"remaining_time":0.05189866817},
{"learn":[4.746422974],"iteration":174,"passed_time":0.1106768561,"remaining_time":0.05122757337},
{"learn":[4.745347927],"iteration":175,"passed_time":0.1112691736,"remaining_time":0.05057689707},
{"learn":[4.737543063],"iteration":176,"passed_time":0.1120168203,"remaining_time":0.04999620794},
{"learn":[4.734058001],"iteration":177,"passed_time":0.1126964427,"remaining_time":0.04938383444},
{"learn":[4.730552418],"iteration":178,"passed_time":0.1134002885,"remaining_time":0.04878112967},
{"learn":[4.7287257],"iteration":179,"passed_time":0.1141080036,"remaining_time":0.04817893485},
{"learn":[4.722207409],"iteration":180,"passed_time":0.1147924933,"remaining_time":0.04756595028},
{"learn":[4.716404156],"iteration":181,"passed_time":0.1153830708,"remaining_time":0.0469139958},
{"learn":[4.713764395],"iteration":182,"passed_time":0.115984681,"remaining_time":0.04626711318},
{"learn":[4.711596985],"iteration":183,"passed_time":0.1166458665,"remaining_time":0.04564403472},
{"learn":[4.707332593],"iteration":184,"passed_time":0.1173132294,"remaining_time":0.04502291508},
{"learn":[4.705320035],"iteration":185,"passed_time":0.1181655271,"remaining_time":0.04447089728},
{"learn":[4.701004581],"iteration":186,"passed_time":0.1188704533,"remaining_time":0.04386129027},
{"learn":[4.699725063],"iteration":187,"passed_time":0.1196399618,"remaining_time":0.04327402874},
{"learn":[4.697998263],"iteration":188,"passed_time":0.1202529718,"remaining_time":0.04262936036},
{"learn":[4.692555934],"iteration":189,"passed_time":0.120963437,"remaining_time":0.0420188781},
{"learn":[4.692044496],"iteration":190,"passed_time":0.1217714424,"remaining_time":0.04144054322},
{"learn":[4.688238875],"iteration":191,"passed_time":0.1224505142,"remaining_time":0.04081683806},
{"learn":[4.68553754],"iteration":192,"passed_time":0.1230668912,"remaining_time":0.04017209402},
{"learn":[4.684759613],"iteration":193,"passed_time":0.1237124824,"remaining_time":0.03953697891},
{"learn":[4.681178888],"iteration":194,"passed_time":0.1245096003,"remaining_time":0.03894915703},
{"learn":[4.676694684],"iteration":195,"passed_time":0.1252634753,"remaining_time":0.03834596182},
{"learn":[4.672338415],"iteration":196,"passed_time":0.1260810462,"remaining_time":0.03776031334},
{"learn":[4.67192808],"iteration":197,"passed_time":0.1267961196,"remaining_time":0.03714229766},
{"learn":[4.666843806],"iteration":198,"passed_time":0.1275135447,"remaining_time":0.03652398015},
{"learn":[4.662566473],"iteration":199,"passed_time":0.1282230697,"remaining_time":0.03590245952},
{"learn":[4.65922601],"iteration":200,"passed_time":0.1287628057,"remaining_time":0.03523360355},
{"learn":[4.658524982],"iteration":201,"passed_time":0.129325382,"remaining_time":0.03457213181},
{"learn":[4.657663871],"iteration":202,"passed_time":0.1299501759,"remaining_time":0.03392787843},
{"learn":[4.654114059],"iteration":203,"passed_time":0.1306249511,"remaining_time":0.03329655617},
{"learn":[4.652413561],"iteration":204,"passed_time":0.1312364892,"remaining_time":0.03264907781},
{"learn":[4.650731762],"iteration":205,"passed_time":0.131868345,"remaining_time":0.03200687987},
{"learn":[4.645919061],"iteration":206,"passed_time":0.1324559718,"remaining_time":0.03135431217},
{"learn":[4.642186479],"iteration":207,"passed_time":0.1330636385,"remaining_time":0.0307069935},
{"learn":[4.632385462],"iteration":208,"passed_time":0.1337051535,"remaining_time":0.03006766611},
{"learn":[4.627575763],"iteration":209,"passed_time":0.1343022617,"remaining_time":0.02941859065},
{"learn":[4.626600553],"iteration":210,"passed_time":0.1348297283,"remaining_time":0.02875515532},
{"learn":[4.621590971],"iteration":211,"passed_time":0.1353802862,"remaining_time":0.02809779524},
{"learn":[4.618165744],"iteration":212,"passed_time":0.1359045425,"remaining_time":0.0274361283},
{"learn":[4.615138999],"iteration":213,"passed_time":0.1364688457,"remaining_time":0.02678360523},
{"learn":[4.613115963],"iteration":214,"passed_time":0.1370896208,"remaining_time":0.02614267188},
{"learn":[4.606796256],"iteration":215,"passed_time":0.13767905,"remaining_time":0.02549612037},
{"learn":[4.60151583],"iteration":216,"passed_time":0.1383018818,"remaining_time":0.02485609857},
{"learn":[4.593331456],"iteration":217,"passed_time":0.1389549125,"remaining_time":0.02422149851},
{"learn":[4.588837494],"iteration":218,"passed_time":0.1396087097,"remaining_time":0.02358685963},
{"learn":[4.585851113],"iteration":219,"passed_time":0.1402184958,"remaining_time":0.02294484476},
{"learn":[4.58403864],"iteration":220,"passed_time":0.1408784481,"remaining_time":0.02231106643},
{"learn":[4.579608179],"iteration":221,"passed_time":0.1414308789,"remaining_time":0.02166058506},
{"learn":[4.579348034],"iteration":222,"passed_time":0.1423463018,"remaining_time":0.02106469937},
{"learn":[4.574559447],"iteration":223,"passed_time":0.1429072341,"remaining_time":0.02041531916},
{"learn":[4.57306201],"iteration":224,"passed_time":0.1436099498,"remaining_time":0.01978625975},
{"learn":[4.568598798],"iteration":225,"passed_time":0.1442747113,"remaining_time":0.01915151035},
{"learn":[4.559272703],"iteration":226,"passed_time":0.1448540239,"remaining_time":0.01850558015},
{"learn":[4.557023415],"iteration":227,"passed_time":0.1453826417,"remaining_time":0.01785400863},
{"learn":[4.55584174],"iteration":228,"passed_time":0.1458837688,"remaining_time":0.01720026969},
{"learn":[4.552604091],"iteration":229,"passed_time":0.1464113684,"remaining_time":0.01655085034},
{"learn":[4.549573147],"iteration":230,"passed_time":0.1470611521,"remaining_time":0.0159157091},
{"learn":[4.547596219],"iteration":231,"passed_time":0.1475619809,"remaining_time":0.0152650325},
{"learn":[4.544407539],"iteration":232,"passed_time":0.1481297741,"remaining_time":0.01462225238},
{"learn":[4.541010074],"iteration":233,"passed_time":0.1487639842,"remaining_time":0.01398635749},
{"learn":[4.538567385],"iteration":234,"passed_time":0.1493976246,"remaining_time":0.01335042603},
{"learn":[4.536231767],"iteration":235,"passed_time":0.149891493,"remaining_time":0.0127026689},
{"learn":[4.531878393],"iteration":236,"passed_time":0.1505049083,"remaining_time":0.01206579433},
{"learn":[4.527370387],"iteration":237,"passed_time":0.1510756604,"remaining_time":0.01142589028},
{"learn":[4.52309405],"iteration":238,"passed_time":0.1516825256,"remaining_time":0.01078913362},
{"learn":[4.518943827],"iteration":239,"passed_time":0.1521787684,"remaining_time":0.01014525123},
{"learn":[4.515524122],"iteration":240,"passed_time":0.1527008765,"remaining_time":0.009504203933},
{"learn":[4.512258311],"iteration":241,"passed_time":0.1532215669,"remaining_time":0.008864057588},
{"learn":[4.503310321],"iteration":242,"passed_time":0.1537920619,"remaining_time":0.008227558866},
{"learn":[4.496827323],"iteration":243,"passed_time":0.1543342425,"remaining_time":0.007590208647},
{"learn":[4.490738319],"iteration":244,"passed_time":0.1550552237,"remaining_time":0.006961663106},
{"learn":[4.48673053],"iteration":245,"passed_time":0.1556705652,"remaining_time":0.006328071757},
{"learn":[4.483526321],"iteration":246,"passed_time":0.1561798847,"remaining_time":0.005690765031},
{"learn":[4.479952576],"iteration":247,"passed_time":0.156811627,"remaining_time":0.005058439582},
{"learn":[4.472223929],"iteration":248,"passed_time":0.1573049354,"remaining_time":0.004422227098},
{"learn":[4.465081601],"iteration":249,"passed_time":0.1577930878,"remaining_time":0.003787034107},
{"learn":[4.456030675],"iteration":250,"passed_time":0.1583014114,"remaining_time":0.00315341457},
{"learn":[4.452173675],"iteration":251,"passed_time":0.1588088497,"remaining_time":0.002520775392},
{"learn":[4.448986738],"iteration":252,"passed_time":0.1593920103,"remaining_time":0.001890023837},
{"learn":[4.445585139],"iteration":253,"passed_time":0.1599749129,"remaining_time":0.001259644983},
{"learn":[4.438218805],"iteration":254,"passed_time":0.1605959357,"remaining_time":0.000629787983},
{"learn":[4.437732565],"iteration":255,"passed_time":0.161184236,"remaining_time":0}
]}